dotdrop/__init__.py
dotdrop/action.py
dotdrop/cfg_aggregator.py
dotdrop/cfg_yaml.py
dotdrop/comparator.py
dotdrop/config.py
dotdrop/dictparser.py
dotdrop/dotdrop.py
dotdrop/dotfile.py
dotdrop/exceptions.py
dotdrop/ftree.py
dotdrop/importer.py
dotdrop/installer.py
dotdrop/jhelpers.py
dotdrop/linktypes.py
dotdrop/logger.py
dotdrop/options.py
dotdrop/profile.py
dotdrop/settings.py
dotdrop/templategen.py
dotdrop/uninstaller.py
dotdrop/updater.py
dotdrop/utils.py
dotdrop/version.py
dotdrop-1.15.0.dist-info/LICENSE
dotdrop-1.15.0.dist-info/METADATA
dotdrop-1.15.0.dist-info/WHEEL
dotdrop-1.15.0.dist-info/entry_points.txt
dotdrop-1.15.0.dist-info/top_level.txt
dotdrop-1.15.0.dist-info/RECORD
