Metadata-Version: 2.1
Name: dotdrop
Version: 1.15.0
Summary: Save your dotfiles once, deploy them everywhere
Home-page: https://github.com/deadc0de6/dotdrop
Download-URL: https://github.com/deadc0de6/dotdrop/archive/v1.15.0.tar.gz
Author: deadc0de6
Author-email: deadc0de6@foo.bar
License: GPLv3
Keywords: dotfiles jinja2
Classifier: Development Status :: 5 - Production/Stable
Classifier: Programming Language :: Python :: 3.7
Classifier: Programming Language :: Python :: 3.8
Classifier: Programming Language :: Python :: 3.9
Classifier: Programming Language :: Python :: 3.10
Classifier: Programming Language :: Python :: 3.11
Classifier: License :: OSI Approved :: GNU General Public License v3 (GPLv3)
Requires-Python: >=3
License-File: LICENSE
Requires-Dist: docopt-ng
Requires-Dist: Jinja2
Requires-Dist: ruamel.yaml
Requires-Dist: python-magic
Requires-Dist: packaging
Requires-Dist: requests
Requires-Dist: tomli-w
Requires-Dist: distro
Requires-Dist: tomli; python_version < "3.11"
Provides-Extra: dev
Requires-Dist: check-manifest; extra == "dev"
Provides-Extra: test
Requires-Dist: coverage; extra == "test"
Requires-Dist: pytest; extra == "test"
Requires-Dist: pytest-cov; extra == "test"
